{
  "STATION 1": {
    "STEP 1": {
      "X": 700,
      "Y": 50,
      "Z": 50,
      "S": 90,
      "B": 0,
      "V": 0
    },
    "STEP 2": {
      "X": 4000,
      "Y": 50,
      "Z": 50,
      "S": 90,
      "B": 0,
      "V": 0
    },
    "STEP 3": {
      "X": 4000,
      "Y": 3000,
      "Z": 1500,
      "S": 90,
      "B": 0,
      "V": 0
    },
    "STEP 4": {
      "X": 4000,
      "Y": 3000,
      "Z": 1500,
      "S": 90,
      "B": 1,
      "V": 0
    },
    "STEP 5": {
      "X": 4000,
      "Y": 3000,
      "Z": 50,
      "S": 90,
      "B": 1,
      "V": 0
    },
    "STEP 6": {
      "X": 4000,
      "Y": 50,
      "Z": 50,
      "S": 90,
      "B": 1,
      "V": 0
    },
    "STEP 7": {
      "X": 500,
      "Y": 50,
      "Z": 50,
      "S": 90,
      "B": 1,
      "V": 0
    },
    "STEP 8": {
      "X": 500,
      "Y": 3000,
      "Z": 2000,
      "S": 90,
      "B": 1,
      "V": 0
    },
    "STEP 9": {
      "X": 500,
      "Y": 3000,
      "Z": 2000,
      "S": 90,
      "B": 1,
      "V": 1
    },
    "STEP 10": {
      "X": 500,
      "Y": 50,
      "Z": 50,
      "S": 90,
      "B": 0,
      "V": 0
    },
    "STEP 11": {
      "X": 4200,
      "Y": 50,
      "Z": 50,
      "S": 90,
      "B": 0,
      "V": 0
    },
    "STEP 12": {
      "X": 4200,
      "Y": 3000,
      "Z": 1500,
      "S": 90,
      "B": 0,
      "V": 0
    },
    "STEP 13": {
      "X": 4200,
      "Y": 3000,
      "Z": 1500,
      "S": 90,
      "B": 1,
      "V": 0
    },
    "STEP 14": {
      "X": 4200,
      "Y": 3000,
      "Z": 50,
      "S": 90,
      "B": 1,
      "V": 0
    },
    "STEP 15": {
      "X": 4200,
      "Y": 3000,
      "Z": 50,
      "S": 90,
      "B": 1,
      "V": 0
    },
    "STEP 16": {
      "X": 600,
      "Y": 50,
      "Z": 50,
      "S": 90,
      "B": 1,
      "V": 0
    },
    "STEP 17": {
      "X": 600,
      "Y": 3000,
      "Z": 2000,
      "S": 90,
      "B": 1,
      "V": 0
    },
    "STEP 18": {
      "X": 600,
      "Y": 3000,
      "Z": 2000,
      "S": 90,
      "B": 1,
      "V": 1
    },
    "STEP 19": {
      "X": 600,
      "Y": 50,
      "Z": 50,
      "S": 90,
      "B": 0,
      "V": 0
    },
    "STEP 20": {
      "X": 4400,
      "Y": 50,
      "Z": 50,
      "S": 90,
      "B": 0,
      "V": 0
    },
    "STEP 21": {
      "X": 4400,
      "Y": 3000,
      "Z": 1500,
      "S": 90,
      "B": 0,
      "V": 0
    },
    "STEP 22": {
      "X": 4400,
      "Y": 3000,
      "Z": 1500,
      "S": 90,
      "B": 1,
      "V": 0
    },
    "STEP 23": {
      "X": 4400,
      "Y": 3000,
      "Z": 50,
      "S": 90,
      "B": 1,
      "V": 0
    },
    "STEP 24": {
      "X": 4400,
      "Y": 50,
      "Z": 50,
      "S": 90,
      "B": 1,
      "V": 0
    },
    "STEP 25": {
      "X": 700,
      "Y": 50,
      "Z": 50,
      "S": 90,
      "B": 1,
      "V": 0
    },
    "STEP 26": {
      "X": 700,
      "Y": 3000,
      "Z": 2000,
      "S": 90,
      "B": 1,
      "V": 0
    },
    "STEP 27": {
      "X": 700,
      "Y": 3000,
      "Z": 2000,
      "S": 90,
      "B": 1,
      "V": 1
    },
    "STEP 28": {
      "X": 700,
      "Y": 50,
      "Z": 50,
      "S": 90,
      "B": 0,
      "V": 0
    },
    "STEP 29": {
      "X": 4600,
      "Y": 50,
      "Z": 50,
      "S": 90,
      "B": 0,
      "V": 0
    },
    "STEP 30": {
      "X": 4600,
      "Y": 3000,
      "Z": 1500,
      "S": 90,
      "B": 0,
      "V": 0
    },
    "STEP 31": {
      "X": 4600,
      "Y": 3000,
      "Z": 1500,
      "S": 90,
      "B": 1,
      "V": 0
    },
    "STEP 32": {
      "X": 4600,
      "Y": 3000,
      "Z": 50,
      "S": 90,
      "B": 1,
      "V": 0
    },
    "STEP 33": {
      "X": 4600,
      "Y": 50,
      "Z": 50,
      "S": 90,
      "B": 1,
      "V": 0
    },
    "STEP 34": {
      "X": 800,
      "Y": 50,
      "Z": 50,
      "S": 90,
      "B": 1,
      "V": 0
    },
    "STEP 35": {
      "X": 800,
      "Y": 3000,
      "Z": 2000,
      "S": 90,
      "B": 1,
      "V": 0
    },
    "STEP 36": {
      "X": 800,
      "Y": 3000,
      "Z": 2000,
      "S": 90,
      "B": 1,
      "V": 1
    },
    "STEP 37": {
      "X": 800,
      "Y": 50,
      "Z": 50,
      "S": 90,
      "B": 0,
      "V": 0
    },
    "STEP 38": {
      "X": 4800,
      "Y": 50,
      "Z": 50,
      "S": 90,
      "B": 0,
      "V": 0
    },
    "STEP 39": {
      "X": 4800,
      "Y": 3000,
      "Z": 1500,
      "S": 90,
      "B": 0,
      "V": 0
    },
    "STEP 40": {
      "X": 4800,
      "Y": 3000,
      "Z": 1500,
      "S": 90,
      "B": 1,
      "V": 0
    },
    "STEP 41": {
      "X": 4800,
      "Y": 3000,
      "Z": 50,
      "S": 90,
      "B": 1,
      "V": 0
    },
    "STEP 42": {
      "X": 4800,
      "Y": 50,
      "Z": 50,
      "S": 90,
      "B": 1,
      "V": 0
    },
    "STEP 43": {
      "X": 900,
      "Y": 50,
      "Z": 50,
      "S": 90,
      "B": 1,
      "V": 0
    },
    "STEP 44": {
      "X": 900,
      "Y": 3000,
      "Z": 2000,
      "S": 90,
      "B": 1,
      "V": 0
    },
    "STEP 45": {
      "X": 900,
      "Y": 3000,
      "Z": 2000,
      "S": 90,
      "B": 1,
      "V": 1
    },
    "STEP 46": {
      "X": 900,
      "Y": 50,
      "Z": 50,
      "S": 90,
      "B": 00,
      "V": 0
    },
    "STEP 47": {
      "X": 5000,
      "Y": 50,
      "Z": 50,
      "S": 90,
      "B": 0,
      "V": 0
    },
    "STEP 48": {
      "X": 5000,
      "Y": 3000,
      "Z": 1500,
      "S": 90,
      "B": 0,
      "V": 0
    },
    "STEP 49": {
      "X": 5000,
      "Y": 3000,
      "Z": 1500,
      "S": 90,
      "B": 1,
      "V": 0
    },
    "STEP 50": {
      "X": 5000,
      "Y": 3000,
      "Z": 50,
      "S": 90,
      "B": 1,
      "V": 0
    },
    "STEP 51": {
      "X": 5000,
      "Y": 50,
      "Z": 50,
      "S": 90,
      "B": 1,
      "V": 0
    },
    "STEP 52": {
      "X": 1000,
      "Y": 50,
      "Z": 50,
      "S": 90,
      "B": 1,
      "V": 0
    },
    "STEP 53": {
      "X": 1000,
      "Y": 3000,
      "Z": 2000,
      "S": 90,
      "B": 1,
      "V": 0
    },
    "STEP 54": {
      "X": 1000,
      "Y": 3000,
      "Z": 2000,
      "S": 90,
      "B": 1,
      "V": 1
    },
    "STEP 55": {
      "X": 1000,
      "Y": 50,
      "Z": 50,
      "S": 90,
      "B": 0,
      "V": 0
    },
    "STEP 56": {
      "X": 5200,
      "Y": 50,
      "Z": 50,
      "S": 90,
      "B": 0,
      "V": 0
    },
    "STEP 57": {
      "X": 5200,
      "Y": 3000,
      "Z": 1500,
      "S": 90,
      "B": 0,
      "V": 0
    },
    "STEP 58": {
      "X": 5200,
      "Y": 3000,
      "Z": 1500,
      "S": 90,
      "B": 1,
      "V": 0
    },
    "STEP 59": {
      "X": 5200,
      "Y": 3000,
      "Z": 50,
      "S": 90,
      "B": 1,
      "V": 0
    },
    "STEP 60": {
      "X": 5200,
      "Y": 50,
      "Z": 50,
      "S": 90,
      "B": 1,
      "V": 0
    },
    "STEP 61": {
      "X": 1200,
      "Y": 50,
      "Z": 50,
      "S": 90,
      "B": 1,
      "V": 0
    },
    "STEP 62": {
      "X": 1200,
      "Y": 3000,
      "Z": 2000,
      "S": 90,
      "B": 1,
      "V": 0
    },
    "STEP 63": {
      "X": 1200,
      "Y": 3000,
      "Z": 2000,
      "S": 90,
      "B": 1,
      "V": 1
    },
    "STEP 64": {
      "X": 1200,
      "Y": 50,
      "Z": 50,
      "S": 90,
      "B": 0,
      "V": 0
    },
    "STEP 65": {
      "X": 700,
      "Y": 50,
      "Z": 50,
      "S": 90,
      "B": 0,
      "V": 0
    }
  }
}